cifkit/__init__.py
cifkit/version.py
cifkit/coordination/__init__.py
cifkit/coordination/bond_distance.py
cifkit/coordination/composition.py
cifkit/coordination/connection.py
cifkit/coordination/filter.py
cifkit/coordination/geometry.py
cifkit/coordination/method.py
cifkit/coordination/site.py
cifkit/coordination/site_distance.py
cifkit/data/__init__.py
cifkit/data/example.py
cifkit/data/mendeleeve_handler.py
cifkit/data/radius_handler.py
cifkit/data/radius_optimization.py
cifkit/data/cifs/GdSb.cif
cifkit/data/cifs/HoSb.cif
cifkit/data/cifs/__init__.py
cifkit/data/cifs/polyhedrons/GdSb_Sb.png
cifkit/figures/__init__.py
cifkit/figures/histogram.py
cifkit/figures/polyhedron.py
cifkit/models/__init__.py
cifkit/models/cif.py
cifkit/models/cif_ensemble.py
cifkit/occupancy/__init__.py
cifkit/occupancy/mixing.py
cifkit/preprocessors/__init__.py
cifkit/preprocessors/environment.py
cifkit/preprocessors/environment_util.py
cifkit/preprocessors/error.py
cifkit/preprocessors/format.py
cifkit/preprocessors/supercell.py
cifkit/preprocessors/supercell_util.py
cifkit/utils/__init__.py
cifkit/utils/bond_pair.py
cifkit/utils/cif_editor.py
cifkit/utils/cif_parser.py
cifkit/utils/cif_sourcer.py
cifkit/utils/distance.py
cifkit/utils/error_messages.py
cifkit/utils/folder.py
cifkit/utils/formula.py
cifkit/utils/log_messages.py
cifkit/utils/prompt.py
cifkit/utils/random.py
cifkit/utils/sort.py
cifkit/utils/string_parser.py
cifkit/utils/unit.py
cifkit-1.1.1.dist-info/licenses/AUTHORS.rst
cifkit-1.1.1.dist-info/licenses/LICENSE.rst
cifkit-1.1.1.dist-info/METADATA
cifkit-1.1.1.dist-info/WHEEL
cifkit-1.1.1.dist-info/top_level.txt
cifkit-1.1.1.dist-info/RECORD
