Metadata-Version: 2.4
Name: cifkit
Version: 1.1.1
Summary: A Python package for coordination geometry and atomic site analysis.
Author-email: Sangjoon Lee <bobleesj@gmail.com>
Maintainer-email: Sangjoon Lee <bobleesj@gmail.com>
Project-URL: Homepage, https://github.com/bobleesj/cifkit/
Project-URL: Issues, https://github.com/bobleesj/cifkit/issues/
Keywords: cif,solid-state,high-throughput,inorganics,crystallography
Classifier: Development Status :: 5 - Production/Stable
Classifier: Environment :: Console
Classifier: Intended Audience :: Developers
Classifier: Intended Audience :: Science/Research
Classifier: License :: OSI Approved :: BSD License
Classifier: Operating System :: MacOS :: MacOS X
Classifier: Operating System :: Microsoft :: Windows
Classifier: Operating System :: POSIX
Classifier: Operating System :: Unix
Classifier: Programming Language :: Python :: 3.11
Classifier: Programming Language :: Python :: 3.12
Classifier: Programming Language :: Python :: 3.13
Classifier: Topic :: Scientific/Engineering :: Physics
Classifier: Topic :: Scientific/Engineering :: Chemistry
Requires-Python: <3.14,>=3.11
License-File: LICENSE.rst
License-File: AUTHORS.rst
Requires-Dist: gemmi
Requires-Dist: matplotlib
Requires-Dist: numpy
Requires-Dist: pyvista
Requires-Dist: scipy
Requires-Dist: bobleesj.utils
Dynamic: license-file
